[
  {
    "titel": "Geef darmkanker geen kans",
    "datum": "maandag 15 september 2025",
    "tijd": "19.00 u - 21.30 u",
    "locatie": "JZ aula Salvator Ziekenhuis, Salvatorstraat 20, 3500 Hasselt",
    "spreker": "Dr. Luc Colemont",
    "prijs": "gratis",
    "parking": "gratis (tickets)",
    "inlichtingen": "midden.limburg@diabetes.be",
    "inschrijven": "www.dlml.be/darmkanker/",
    "organisatie": [
      "Diabetes Liga",
      "Eerstelijnszone Herkenrode",
      "Wildgroei",
      "Jessa Ziekenhuis",
      "Stoma Ilco"
    ]
  },
  {
    "titel": "Nieuwe technieken nieuwe medicatie",
    "datum": "donderdag 27 november 2025",
    "tijd": "20.00 u - 22.00 u",
    "locatie": "JZ aula Salvator Ziekenhuis, Salvatorstraat 20, 3500 Hasselt",
    "spreker": "Eddy Foulon, Apotheker",
    "prijs": "gratis",
    "parking": "gratis (tickets)",
    "inlichtingen": "midden.limburg@diabetes.be",
    "inschrijven": "www.dlml.be/nieuwetechnieken/"
  },
  {
    "titel": "Praatcafé",
    "datum": "donderdag 16 oktober 2025",
    "tijd": "20.00 u - 22.00 u",
    "locatie": "JZ aula Salvator Ziekenhuis, Salvatorstraat 20, 3500 Hasselt",
    "spreker": "team diabetesconventie Hasselt",
    "prijs": "gratis",
    "parking": "gratis (tickets)",
    "methode": "groepsgesprek",
    "inlichtingen": "midden.limburg@diabetes.be",
    "inschrijven": "www.dlml.be/praatcafe/"
  },
  {
    "titel": "All-in Holiday",
    "datum": "dinsdag 9 december 2025",
    "tijd": "19.00 u - 21.00 u",
    "locatie": "Personeelscafetaria az Vesalius, Hazelereik 51, 3700 Tongeren",
    "spreker": "Diëtisten van de diabetesconventie AZ Vesalius",
    "prijs": "gratis",
    "parking": "gratis",
    "inlichtingen": "midden.limburg@diabetes.be",
    "inschrijven": "www.dlml.be/holiday/"
  }
]